MANIFEST.in
README.rst
setup.cfg
setup.py
pOCCI/CORE.py
pOCCI/__init__.py
pOCCI/occi.py
pOCCI/occi_libs.py
pOCCI/pOCCI-parse.1
pOCCI/pOCCI.1
pOCCI/pOCCI.cfg
pOCCI/pOCCI.py
pOCCI/pOCCI_parse.py
pOCCI/render.py
pOCCI/render_base.py
pOCCI/render_http.py
pOCCI/render_json.py
pOCCI/render_text.py
pOCCI/render_uri.py
pOCCI/transport.py
pOCCI/version.py
pOCCI.egg-info/PKG-INFO
pOCCI.egg-info/SOURCES.txt
pOCCI.egg-info/dependency_links.txt
pOCCI.egg-info/entry_points.txt
pOCCI.egg-info/requires.txt
pOCCI.egg-info/top_level.txt