Metadata-Version: 1.1
Name: pOCCI
Version: 1.0.3
Summary: OCCI Compliance Testing Tool
Home-page: https://github.com/CESNET/pOCCI
Author: CESNET
Author-email: cloud@rt4.cesnet.cz
License: MIT
Keywords: OCCI cloud compliance testing pycurl
Platform: UNKNOWN
Classifier: Development Status :: 3 - Alpha
Classifier: Intended Audience :: Developers
Classifier: Intended Audience :: Information Technology
Classifier: Topic :: Scientific/Engineering :: Interface Engine/Protocol Translator
Classifier: Topic :: System :: Distributed Computing
Classifier: License :: OSI Approved :: MIT License
Classifier: Programming Language :: Python :: 2
Classifier: Programming Language :: Python :: 2.6
Classifier: Programming Language :: Python :: 2.7
Classifier: Programming Language :: Python :: 3
Classifier: Programming Language :: Python :: 3.2
Classifier: Programming Language :: Python :: 3.3
Classifier: Programming Language :: Python :: 3.4
